habil/__init__.py
habil/client.py
habil/tasking.py
habil/elements/__init__.py
habil/elements/daily.py
habil/elements/habit.py
habil/elements/reward.py
habil/elements/todo.py
habil/sub/__init__.py
habil/sub/tag.py
habil_base/__init__.py
habil_base/exceptions.py
habil_base/habiBaseItem.py
habil_base/habiToken.py
habil_base/habiUItem.py
habil_case/__init__.py
habil_case/tag.py
habil_case/task.py
habil_case/user.py
habil_case/user_ext.py
habil_ext/__init__.py
habil_ext/counterDaily.py
habil_map/__init__.py
habil_map/habiMapAttr.py
habil_map/habiMapCase.py
habil_map/habiMapMeta.py
habil_map/habiMapResponse.py
habil_utils/__init__.py
habil-0.1.0.dist-info/LICENSE
habil-0.1.0.dist-info/METADATA
habil-0.1.0.dist-info/WHEEL
habil-0.1.0.dist-info/top_level.txt
habil-0.1.0.dist-info/RECORD
