Metadata-Version: 2.1
Name: habil
Version: 0.1.0
Summary: a lite python wrapper for habitica api
Home-page: https://github.com/ZackaryW/habil
Author: ZackaryW
Author-email: zackaryxcw@gmail.com
License: MIT
Platform: UNKNOWN
Classifier: Development Status :: 3 - Alpha
Classifier: Intended Audience :: Developers
Classifier: License :: OSI Approved :: MIT License
Classifier: Programming Language :: Python :: 3
Classifier: Programming Language :: Python :: 3.10
Requires-Python: >=3.10
License-File: LICENSE
Requires-Dist: requests
